README.rst
setup.py
snipeit_ammar/Accessories.py
snipeit_ammar/Assets.py
snipeit_ammar/AssetsMaintenances.py
snipeit_ammar/Categories.py
snipeit_ammar/Company.py
snipeit_ammar/Components.py
snipeit_ammar/Consumables.py
snipeit_ammar/DataUtil.py
snipeit_ammar/Fieldsets.py
snipeit_ammar/Licenses.py
snipeit_ammar/Locations.py
snipeit_ammar/Maintenances.py
snipeit_ammar/Manufacturers.py
snipeit_ammar/Models.py
snipeit_ammar/StatusLabels.py
snipeit_ammar/Users.py
snipeit_ammar/__init__.py
snipeit_ammar.egg-info/PKG-INFO
snipeit_ammar.egg-info/SOURCES.txt
snipeit_ammar.egg-info/dependency_links.txt
snipeit_ammar.egg-info/not-zip-safe
snipeit_ammar.egg-info/requires.txt
snipeit_ammar.egg-info/top_level.txt