Metadata-Version: 2.1
Name: snipeit-ammar
Version: 1.3
Summary: Python library to access the SnipeIT API-forked
Home-page: https://github.com/ammar0466/SnipeIT-PythonAPI
Author: Ammar Ibrahim
Author-email: ammar@webkaido.com
License: MIT
Platform: UNKNOWN
